de_sim/__init__.py
de_sim/_version.py
de_sim/checkpoint.py
de_sim/errors.py
de_sim/event.py
de_sim/event_message.py
de_sim/simulation_checkpoint_object.py
de_sim/simulation_config.py
de_sim/simulation_metadata.py
de_sim/simulation_object.py
de_sim/simulator.py
de_sim/template_sim_objs.py
de_sim/utilities.py
de_sim/visualize.py
de_sim/config/__init__.py
de_sim/config/core.default.cfg
de_sim/config/core.py
de_sim/config/core.schema.cfg
de_sim/config/debug.default.cfg
de_sim/examples/__init__.py
de_sim/examples/debug_logs.py
de_sim/examples/minimal_simulation.py
de_sim/examples/phold.py
de_sim/examples/random_walk.py
de_sim/examples/sirs.py
de_sim/examples/config/__init__.py
de_sim/examples/config/core.py
de_sim/testing/__init__.py
de_sim/testing/example_simulation_objects.py
de_sim/testing/mock_simulation_object.py
de_sim/testing/some_message_types.py
de_sim/testing/utilities_for_testing.py
de_sim-1.0.5.dist-info/LICENSE
de_sim-1.0.5.dist-info/METADATA
de_sim-1.0.5.dist-info/WHEEL
de_sim-1.0.5.dist-info/entry_points.txt
de_sim-1.0.5.dist-info/top_level.txt
de_sim-1.0.5.dist-info/RECORD
