Metadata-Version: 2.1
Name: de-sim
Version: 1.0.5
Summary: object-oriented, discrete-event simulation tool for data-intensive modeling of complex systems
Home-page: https://github.com/KarrLab/de_sim
Author: Karr Lab
Author-email: info@karrlab.org
License: MIT
Download-URL: https://github.com/KarrLab/de_sim
Keywords: computational modeling,data-driven modeling,discrete-event simulation,DES,object-oriented programming,Python
Platform: UNKNOWN
Classifier: Development Status :: 4 - Beta
Classifier: Intended Audience :: Science/Research
Classifier: License :: OSI Approved :: MIT License
Classifier: Natural Language :: English
Classifier: Operating System :: OS Independent
Classifier: Programming Language :: Python :: 3.7
Classifier: Programming Language :: Python :: 3
Classifier: Programming Language :: Python
Classifier: Topic :: Scientific/Engineering :: Bio-Informatics
Classifier: Topic :: Scientific/Engineering
Requires-Dist: configobj
Requires-Dist: logging2
Requires-Dist: matplotlib
Requires-Dist: numpy
Requires-Dist: progressbar2 (>=3.39)
Requires-Dist: pympler
Requires-Dist: setuptools
Requires-Dist: wc-utils[git] (>=0.0.16)
Provides-Extra: all
Requires-Dist: capturer ; extra == 'all'
Requires-Dist: ipykernel ; extra == 'all'
Requires-Dist: nbconvert ; extra == 'all'
Requires-Dist: nbformat ; extra == 'all'
Requires-Dist: sphinx (>=1.8) ; extra == 'all'
Requires-Dist: sphinx-fontawesome ; extra == 'all'
Requires-Dist: sphinx-rtd-theme (>=0.4.2) ; extra == 'all'
Requires-Dist: sphinxcontrib-addmetahtml (>=0.1.1) ; extra == 'all'
Requires-Dist: sphinxcontrib-bibtex ; extra == 'all'
Requires-Dist: sphinxcontrib-googleanalytics (>=0.1.1) ; extra == 'all'
Requires-Dist: sphinxcontrib-spelling ; extra == 'all'
Requires-Dist: sphinxprettysearchresults ; extra == 'all'
Provides-Extra: docs
Requires-Dist: sphinx (>=1.8) ; extra == 'docs'
Requires-Dist: sphinx-fontawesome ; extra == 'docs'
Requires-Dist: sphinx-rtd-theme (>=0.4.2) ; extra == 'docs'
Requires-Dist: sphinxcontrib-addmetahtml (>=0.1.1) ; extra == 'docs'
Requires-Dist: sphinxcontrib-bibtex ; extra == 'docs'
Requires-Dist: sphinxcontrib-googleanalytics (>=0.1.1) ; extra == 'docs'
Requires-Dist: sphinxcontrib-spelling ; extra == 'docs'
Requires-Dist: sphinxprettysearchresults ; extra == 'docs'
Provides-Extra: tests
Requires-Dist: capturer ; extra == 'tests'
Requires-Dist: ipykernel ; extra == 'tests'
Requires-Dist: nbconvert ; extra == 'tests'
Requires-Dist: nbformat ; extra == 'tests'
